{"nodes": [{"id": "c_users_chakr_onedrive_desktop_zero_brain_second_brain_starter_archon_packages_core_src_utils_commands_ts", "label": "commands.ts", "file_type": "code", "source_file": "C:\\Users\\chakr\\OneDrive\\Desktop\\zero BRAIN\\second-brain-starter\\Archon\\packages\\core\\src\\utils\\commands.ts", "source_location": "L1"}, {"id": "utils_commands_findmarkdownfilesrecursive", "label": "findMarkdownFilesRecursive()", "file_type": "code", "source_file": "C:\\Users\\chakr\\OneDrive\\Desktop\\zero BRAIN\\second-brain-starter\\Archon\\packages\\core\\src\\utils\\commands.ts", "source_location": "L15"}], "edges": [{"source": "c_users_chakr_onedrive_desktop_zero_brain_second_brain_starter_archon_packages_core_src_utils_commands_ts", "target": "promises", "relation": "imports_from", "context": "import", "confidence": "EXTRACTED", "source_file": "C:\\Users\\chakr\\OneDrive\\Desktop\\zero BRAIN\\second-brain-starter\\Archon\\packages\\core\\src\\utils\\commands.ts", "source_location": "L4", "weight": 1.0}, {"source": "c_users_chakr_onedrive_desktop_zero_brain_second_brain_starter_archon_packages_core_src_utils_commands_ts", "target": "path", "relation": "imports_from", "context": "import", "confidence": "EXTRACTED", "source_file": "C:\\Users\\chakr\\OneDrive\\Desktop\\zero BRAIN\\second-brain-starter\\Archon\\packages\\core\\src\\utils\\commands.ts", "source_location": "L5", "weight": 1.0}, {"source": "c_users_chakr_onedrive_desktop_zero_brain_second_brain_starter_archon_packages_core_src_utils_commands_ts", "target": "utils_commands_findmarkdownfilesrecursive", "relation": "contains", "confidence": "EXTRACTED", "source_file": "C:\\Users\\chakr\\OneDrive\\Desktop\\zero BRAIN\\second-brain-starter\\Archon\\packages\\core\\src\\utils\\commands.ts", "source_location": "L15", "weight": 1.0}], "raw_calls": [{"caller_nid": "utils_commands_findmarkdownfilesrecursive", "callee": "filter", "is_member_call": true, "source_file": "C:\\Users\\chakr\\OneDrive\\Desktop\\zero BRAIN\\second-brain-starter\\Archon\\packages\\core\\src\\utils\\commands.ts", "source_location": "L21"}, {"caller_nid": "utils_commands_findmarkdownfilesrecursive", "callee": "split", "is_member_call": true, "source_file": "C:\\Users\\chakr\\OneDrive\\Desktop\\zero BRAIN\\second-brain-starter\\Archon\\packages\\core\\src\\utils\\commands.ts", "source_location": "L21"}, {"caller_nid": "utils_commands_findmarkdownfilesrecursive", "callee": "join", "is_member_call": false, "source_file": "C:\\Users\\chakr\\OneDrive\\Desktop\\zero BRAIN\\second-brain-starter\\Archon\\packages\\core\\src\\utils\\commands.ts", "source_location": "L23"}, {"caller_nid": "utils_commands_findmarkdownfilesrecursive", "callee": "readdir", "is_member_call": false, "source_file": "C:\\Users\\chakr\\OneDrive\\Desktop\\zero BRAIN\\second-brain-starter\\Archon\\packages\\core\\src\\utils\\commands.ts", "source_location": "L25"}, {"caller_nid": "utils_commands_findmarkdownfilesrecursive", "callee": "startsWith", "is_member_call": true, "source_file": "C:\\Users\\chakr\\OneDrive\\Desktop\\zero BRAIN\\second-brain-starter\\Archon\\packages\\core\\src\\utils\\commands.ts", "source_location": "L28"}, {"caller_nid": "utils_commands_findmarkdownfilesrecursive", "callee": "isDirectory", "is_member_call": true, "source_file": "C:\\Users\\chakr\\OneDrive\\Desktop\\zero BRAIN\\second-brain-starter\\Archon\\packages\\core\\src\\utils\\commands.ts", "source_location": "L32"}, {"caller_nid": "utils_commands_findmarkdownfilesrecursive", "callee": "join", "is_member_call": false, "source_file": "C:\\Users\\chakr\\OneDrive\\Desktop\\zero BRAIN\\second-brain-starter\\Archon\\packages\\core\\src\\utils\\commands.ts", "source_location": "L36"}, {"caller_nid": "utils_commands_findmarkdownfilesrecursive", "callee": "push", "is_member_call": true, "source_file": "C:\\Users\\chakr\\OneDrive\\Desktop\\zero BRAIN\\second-brain-starter\\Archon\\packages\\core\\src\\utils\\commands.ts", "source_location": "L39"}, {"caller_nid": "utils_commands_findmarkdownfilesrecursive", "callee": "isFile", "is_member_call": true, "source_file": "C:\\Users\\chakr\\OneDrive\\Desktop\\zero BRAIN\\second-brain-starter\\Archon\\packages\\core\\src\\utils\\commands.ts", "source_location": "L40"}, {"caller_nid": "utils_commands_findmarkdownfilesrecursive", "callee": "endsWith", "is_member_call": true, "source_file": "C:\\Users\\chakr\\OneDrive\\Desktop\\zero BRAIN\\second-brain-starter\\Archon\\packages\\core\\src\\utils\\commands.ts", "source_location": "L40"}, {"caller_nid": "utils_commands_findmarkdownfilesrecursive", "callee": "push", "is_member_call": true, "source_file": "C:\\Users\\chakr\\OneDrive\\Desktop\\zero BRAIN\\second-brain-starter\\Archon\\packages\\core\\src\\utils\\commands.ts", "source_location": "L41"}, {"caller_nid": "utils_commands_findmarkdownfilesrecursive", "callee": "basename", "is_member_call": false, "source_file": "C:\\Users\\chakr\\OneDrive\\Desktop\\zero BRAIN\\second-brain-starter\\Archon\\packages\\core\\src\\utils\\commands.ts", "source_location": "L42"}, {"caller_nid": "utils_commands_findmarkdownfilesrecursive", "callee": "join", "is_member_call": false, "source_file": "C:\\Users\\chakr\\OneDrive\\Desktop\\zero BRAIN\\second-brain-starter\\Archon\\packages\\core\\src\\utils\\commands.ts", "source_location": "L43"}]}